obscuratee/__init__.py
obscuratee/main.py
obscuratee-1.1.1.dist-info/licenses/LICENSE
obscuratee-1.1.1.dist-info/METADATA
obscuratee-1.1.1.dist-info/WHEEL
obscuratee-1.1.1.dist-info/entry_points.txt
obscuratee-1.1.1.dist-info/top_level.txt
obscuratee-1.1.1.dist-info/RECORD
