Metadata-Version: 2.4
Name: obscuratee
Version: 1.1.1
Summary: A terminal toy that spits out manatee facts gathered by years of research.
Author-email: sn3cc <sn33zyhub@gmail.com>
License: MIT
Requires-Python: >=3.6
License-File: LICENSE
Dynamic: license-file
